pyllments/__init__.py
pyllments/__main__.py
pyllments/_version.py
pyllments/config.py
pyllments/logging.py
pyllments/assets/favicon.ico
pyllments/assets/css/global.css
pyllments/assets/file_icons/tabler-icons-outline.min.css
pyllments/assets/file_icons/tabler-icons-outline.min.css.map
pyllments/assets/file_icons/fonts/tabler-icons-outline.woff2
pyllments/base/__init__.py
pyllments/base/component_base.py
pyllments/base/element_base.py
pyllments/base/listing_base.py
pyllments/base/model_base.py
pyllments/base/payload_base.py
pyllments/cli/__init__.py
pyllments/cli/app.py
pyllments/cli/serve_helper.py
pyllments/cli/commands/recipe.py
pyllments/cli/commands/serve.py
pyllments/common/__init__.py
pyllments/common/collections.py
pyllments/common/param.py
pyllments/common/pydantic_models.py
pyllments/common/resource_loader.py
pyllments/common/style_helpers.py
pyllments/common/tokenizers.py
pyllments/common/type_utils.py
pyllments/elements/__init__.py
pyllments/elements/api/__init__.py
pyllments/elements/api/api_element.py
pyllments/elements/api/api_model.py
pyllments/elements/chat_interface/__init__.py
pyllments/elements/chat_interface/chat_interface_element.py
pyllments/elements/chat_interface/chat_interface_model.py
pyllments/elements/chat_interface/css/chat_input_view.css
pyllments/elements/chat_interface/css/chatfeed_view.css
pyllments/elements/chat_interface/css/payload_assistant_row.css
pyllments/elements/chat_interface/css/payload_user_row.css
pyllments/elements/chat_interface/css/send_button_view.css
pyllments/elements/chunker/__init__.py
pyllments/elements/chunker/splitters.py
pyllments/elements/chunker/text_chunker_element.py
pyllments/elements/chunker/text_chunker_model.py
pyllments/elements/context_builder/__init__.py
pyllments/elements/context_builder/context_builder_element.py
pyllments/elements/context_builder/to_message.py
pyllments/elements/discord/__init__.py
pyllments/elements/discord/discord_element.py
pyllments/elements/discord/discord_model.py
pyllments-0.0.4.dist-info/METADATA
pyllments-0.0.4.dist-info/WHEEL
pyllments-0.0.4.dist-info/entry_points.txt
pyllments-0.0.4.dist-info/licenses/LICENSE
pyllments-0.0.4.dist-info/RECORD
