Metadata-Version: 2.4
Name: pyllments
Version: 0.0.4
Summary: A Python framework for building modular, extensible LLM applications through composable Elements  in a flow-based architecture. Pyllments enables developers to create both graphical and API-based  LLM applications by connecting specialized Elements through a flexible port system, with built-in  support for UI components and LLM integrations.
License-Expression: Apache-2.0
License-File: LICENSE
Requires-Python: >=3.10
Requires-Dist: bokeh
Requires-Dist: bokeh-fastapi
Requires-Dist: discord-py>=2.4.0
Requires-Dist: fastapi[standard]
Requires-Dist: jinja2
Requires-Dist: jsonlines
Requires-Dist: langchain-text-splitters
Requires-Dist: litellm>=1.57.3
Requires-Dist: loguru
Requires-Dist: mcp>=1.3.0
Requires-Dist: numpy
Requires-Dist: panel
Requires-Dist: pillow-heif
Requires-Dist: python-dotenv
Requires-Dist: python-telegram-bot>=21.10
Requires-Dist: ruamel-yaml
Requires-Dist: sqlite-utils>=3.38
Requires-Dist: telethon>=1.38.1
Requires-Dist: tiktoken
Requires-Dist: typer
Provides-Extra: full
Requires-Dist: chromadb; extra == 'full'
Requires-Dist: duckdb; extra == 'full'
Requires-Dist: lancedb; extra == 'full'
Requires-Dist: opencv-python; extra == 'full'
Requires-Dist: pdfminer-six; extra == 'full'
Requires-Dist: pikepdf; extra == 'full'
Requires-Dist: pytesseract; extra == 'full'
Requires-Dist: sentence-transformers[onnx-gpu]; extra == 'full'
Requires-Dist: unstructured; extra == 'full'
